AUTHORS.rst
CHANGES.rst
LICENSE.txt
MANIFEST.in
README.rst
setup.py
py_wsse.egg-info/PKG-INFO
py_wsse.egg-info/SOURCES.txt
py_wsse.egg-info/dependency_links.txt
py_wsse.egg-info/not-zip-safe
py_wsse.egg-info/requires.txt
py_wsse.egg-info/top_level.txt
test/__init__.py
wsse/__init__.py
wsse/constants.py
wsse/encryption.py
wsse/exceptions.py
wsse/signing.py
wsse/suds.py
wsse/xml.py