Metadata-Version: 1.1
Name: py-wsse
Version: 0.1
Summary: WS-Security (SOAP WSSE) signing and encryption
Home-page: https://github.com/orcasgit/py-wsse/
Author: ORCAS, Inc
Author-email: orcastech@orcasinc.com
License: UNKNOWN
Platform: UNKNOWN
Classifier: Environment :: Web Environment
Classifier: Intended Audience :: Developers
Classifier: License :: OSI Approved :: BSD License
Classifier: Operating System :: OS Independent
Classifier: Programming Language :: Python
Classifier: Programming Language :: Python :: 2
Classifier: Programming Language :: Python :: 2.7
Classifier: Programming Language :: Python :: 3
Classifier: Programming Language :: Python :: 3.3
Classifier: Programming Language :: Python :: 3.4
Classifier: Programming Language :: Python :: Implementation :: CPython
